Workbook

Sheet FODA
C3: FORTALEZAS | E3: DEBILIDADES
C4: F1 | D4: Experiencia consolidada en el rubro automotriz nacional. | E4: D1 | F4: Alta dependencia de vehículos importados (vulnerable al tipo de cambio).
C5: F2 | D5: Alianzas estratégicas con marcas internacionales. | E5: D2 | F5: Limitada oferta de vehículos eléctricos o híbridos.
C6: F3 | D6: Personal técnico certificado y capacitado | E6: D3 | F6: Procesos administrativos poco automatizados.
C7: F4 | D7: Implementación de sistemas digitales de ventas y CRM. | E7: D4 | F7: Falta de diversificación en líneas de negocio.
C8: F5 | D8: Buen posicionamiento de marca y reputación comercial. | E8: D5 | F8: Escasa presencia en regiones fuera de Lima.
C9: F6 | D9: Políticas de servicio postventa y atención al cliente. | E9: D6 | F9: Dependencia de proveedores extranjeros.
C10: F7 | D10: Capacidad de adaptación a regulaciones ambientales. | E10: D7 | F10: Baja inversión en innovación tecnológica.
C11: F8 | D11: Eficiencia en los procesos logísticos de importación y distribución. | E11: D8 | F11: Falta de alianzas financieras para crédito vehicular.
C12: F9 | D12: Sistema contable y de control interno automatizado. | E12: D9 | F12: Ausencia de un sistema robusto de evaluación del desempeño.
C13: F10 | D13: Implementación de prácticas de sostenibilidad (reciclaje, emisiones). | E13: D10 | F13: Baja participación en licitaciones del sector público o corporativo.
C14: F11 | D14: Posicionamiento en segmentos de gama media y alta. | E14: D11 | F14: Poca innovación en estrategias de ventas personalizadas
C15: F12 | D15: Alta satisfacción del cliente según encuestas internas. | E15: D12
C16: OPORTUNIDADES | E16: AMENAZAS
C17: O1 | D17: Crecimiento de canales digitales y redes sociales para mejorar experiencia de compra | E17: A1 | F17: Volatilidad del tipo de cambio que encarece la importación de vehículos
C18: O2 | D18: Normas de Indecopi (garantía, postventa) que aumentan confianza del cliente | E18: A2 | F18: Ingreso de fabricantes globales (Toyota, Honda, Nissan) que abren canales directos de distribución eliminando intermediarios
C19: O3 | D19: Creciente demanda del consumidor por conectividad vehicular y control de vehículo vía aplicaciones móviles | E19: A3 | F19: Cambios frecuentes en legislación laboral y tributaria (AFP, EPS) que incrementan costos operacionales
C20: O4 | D20: Altas inversiones requeridas en infraestructura como barrera de entrada para nuevos competidores | E20: A4 | F20: Normativas del MTC que obligan incorporación de tecnologías de seguridad (ABS, airbag, control estabilidad)
C21: O5 | D21: Creación del Fondo de Promoción de Electromovilidad (FONCOER) y financiamiento verde | E21: A5 | F21: Tasas de interés (TEA) elevadas que limitan el acceso al crédito vehicular
C22: O6 | D22: Mayor interés del público joven en movilidad personal (motos, autos) | E22: A6 | F22: Competencia con marcas globales de alto prestigio y gran poder de negociación
C23: O7 | D23: Mayor conciencia ambiental entre segmentos ABC que impulsa preferencia por vehículos híbridos y eléctricos | E23: A7 | F23: Ausencia de infraestructura de carga pública para vehículos eléctricos en Perú (Lima: 80%, interior: 20%)
C24: O8 | D24: Mayor demanda por vehículos utilitarios (SUV y camionetas) por seguridad y versatilidad | E24: A8 | F24: Regulaciones ambientales más estrictas sobre emisiones vehiculares (ej. Euro VI+)
C25: O9 | D25: Tendencia de concentración y consolidación entre grupos concesionarios que facilita alianzas estratégicas | E25: A9
C26: O10 | D26: Disponibilidad en mercado de herramientas de IA para el sector automotriz | E26: A10

Sheet CAME
B1: CASO DE ESTUDIO: INCAMOTORS S.A.C. Análisis del CAME
B2: RESULTADOS (CORREGIR - AFRONTAR - MANTENER - EXPLORAR)
D4: ANÁLISIS EXTERNO
D5: OPORTUNIDADES | F5: AMENAZAS
B6: ANALISIS INTERNO | C6: FORTALEZAS | D6: E1 | E6: =VLOOKUP(D6,'ESTRATEGIAS FO'!F$5:H21,3,FALSE) -> Potenciar el CRM y la plataforma digital para captar clientes vía redes sociales y automatizar cotizaciones y seguimiento. | F6: E1 | G6: =VLOOKUP(F6,'ESTRATEGIAS DA'!F$5:H21,3,FALSE) -> Diversificar proveedores y asegurar compras programadas o contratos forward para reducir el impacto del tipo de cambio.
D7: E2 | E7: =VLOOKUP(D7,'ESTRATEGIAS FO'!F$5:H22,3,FALSE) -> Lanzar una línea que tenga motos y autos compactos siendo respaldada por la fortaleza de marca para atraer al segmento joven. | F7: E2 | G7: =VLOOKUP(F7,'ESTRATEGIAS DA'!F$5:H22,3,FALSE) -> Negociar contratos de abastecimiento más estables y asegurar acuerdos mínimos para evitar ser desplazados por distribuidores directos.
D8: E3 | E8: =VLOOKUP(D8,'ESTRATEGIAS FO'!F$5:H23,3,FALSE) -> Introducir modelos híbridos/eléctricos mediante acuerdos internacionales y financiamiento verde para liderar la electromovilidad. | F8: E3 | G8: =VLOOKUP(F8,'ESTRATEGIAS DA'!F$5:H23,3,FALSE) -> Implementar automatización básica (contable y RR.HH.) para evitar sanciones y sobrecostos por errores manuales.
D9: E4 | E9: =VLOOKUP(D9,'ESTRATEGIAS FO'!F$5:H24,3,FALSE) -> Garantizar disponibilidad inmediata de SUVs/camionetas mediante logística optimizada, superando tiempos de entrega de la competencia. | F9: E4 | G9: =VLOOKUP(F9,'ESTRATEGIAS DA'!F$5:H24,3,FALSE) -> Asignar inversión mínima obligatoria para cumplir con tecnología reglamentaria (ABS, airbag), evitando multas y paralización de ventas.
D10: E5 | E10: =VLOOKUP(D10,'ESTRATEGIAS FO'!F$5:H25,3,FALSE) -> Fortalecer y estandarizar la postventa para cumplir y superar Indecopi, elevando la confianza y fidelización del cliente. | F10: E5 | G10: =VLOOKUP(F10,'ESTRATEGIAS DA'!F$5:H25,3,FALSE) -> Establecer convenios urgentes con financieras/fintech para evitar caída drástica en ventas por falta de acceso al crédito vehicular.
D11: E6 | E11: =VLOOKUP(D11,'ESTRATEGIAS FO'!F$5:H26,3,FALSE) -> Crear una linea que impulse vehículos híbridos/eléctricos, alineados a la preferencia ambiental de segmentos premium. | F11: E6 | G11: =VLOOKUP(F11,'ESTRATEGIAS DA'!F$5:H26,3,FALSE) -> Ajustar el portafolio eléctrico a modelos híbridos o mild-hybrid que no dependan de cargadores públicos para no perder competitividad.
D12: E7 | E12: =VLOOKUP(D12,'ESTRATEGIAS FO'!F$5:H27,3,FALSE) -> Ofrecer servicios avanzados de conectividad (telemetría, apps, diagnósticos remotos) gracias al personal técnico especializado. | F12: E7 | G12: =VLOOKUP(F12,'ESTRATEGIAS DA'!F$5:H27,3,FALSE) -> Implementar un sistema básico de evaluación de desempeño para alinear servicio, tiempos y calidad frente a competidores globales.
D13: E8 | E13: =VLOOKUP(D13,'ESTRATEGIAS FO'!F$5:H28,3,FALSE) -> Formar la red “Incamotors Network” integrando concesionarios medianos mediante experiencia operativa y procesos consolidados. | F13: E8 | G13: =VLOOKUP(F13,'ESTRATEGIAS DA'!F$5:H28,3,FALSE) -> #N/A
D14: E9 | E14: =VLOOKUP(D14,'ESTRATEGIAS FO'!F$5:H29,3,FALSE) -> Implementar IA para personalizar ofertas y mejorar la experiencia del cliente basándose en el historial de satisfacción. | F14: E9 | G14: =VLOOKUP(F14,'ESTRATEGIAS DA'!F$5:H29,3,FALSE) -> #N/A
D15: E10 | E15: =VLOOKUP(D15,'ESTRATEGIAS FO'!F$5:H30,3,FALSE) -> Impulsar un portafolio premium de SUVs dirigido a segmentos de mayor valor alineado a la tendencia utilitaria. | F15: E10 | G15: =VLOOKUP(F15,'ESTRATEGIAS DA'!F$5:H30,3,FALSE) -> #N/A
C16: DEBILIDADES | D16: E1 | E16: =VLOOKUP(D16,'ESTRATEGIAS FA'!F5:H21,3,FALSE) -> Reforzar la consolidación de importaciones y la planificación de compras para reducir el impacto del tipo de cambio sobre el costo del vehículo. | F16: E1 | G16: =VLOOKUP(F6,'ESTRATEGIAS DO'!F$5:H21,3,FALSE) -> Digitalizar y automatizar procesos administrativos y comerciales integrando CRM, ventas online y atención digital.
D17: E2 | E17: =VLOOKUP(D17,'ESTRATEGIAS FA'!F6:H22,3,FALSE) -> Negociar acuerdos exclusivos y programas de fidelización con marcas aliadas para evitar ser desplazados por canales directos. | F17: E2 | G17: =VLOOKUP(F7,'ESTRATEGIAS DO'!F$5:H22,3,FALSE) -> Implementar IA para personalizar ofertas, recomendar modelos y automatizar propuestas comerciales.
D18: E3 | E18: =VLOOKUP(D18,'ESTRATEGIAS FA'!F7:H23,3,FALSE) -> Optimizar productividad técnica mediante especialización y digitalización de procesos para compensar los mayores costos laborales. | F18: E3 | G18: =VLOOKUP(F8,'ESTRATEGIAS DO'!F$5:H23,3,FALSE) -> Expandir portafolio eco mediante alianzas estratégicas y uso del FONCOER para ingresar al mercado eléctrico.
D19: E4 | E19: =VLOOKUP(D19,'ESTRATEGIAS FA'!F8:H24,3,FALSE) -> Integrar módulos digitales de seguimiento técnico para asegurar cumplimiento y actualización de tecnologías obligatorias. | F19: E4 | G19: =VLOOKUP(F9,'ESTRATEGIAS DO'!F$5:H24,3,FALSE) -> Integrarse a redes de concesionarios para compras conjuntas, economías de escala y reducción del riesgo cambiario.
D20: E5 | E20: =VLOOKUP(D20,'ESTRATEGIAS FA'!F9:H25,3,FALSE) -> Fortalecer procesos de reducción de emisiones y trazabilidad ambiental para minimizar multas y adelantarse a regulaciones. | F20: E5 | G20: =VLOOKUP(F10,'ESTRATEGIAS DO'!F$5:H25,3,FALSE) -> Establecer convenios con financieras/fintech para ofrecer créditos accesibles a jóvenes (autos compactos, motos).
D21: E6 | E21: =VLOOKUP(D21,'ESTRATEGIAS FA'!F10:H26,3,FALSE) -> Diferenciar el portafolio con paquetes de valor, servicio boutique y garantías premium para competir frente a marcas de mayor prestigio. | F21: E6 | G21: =VLOOKUP(F11,'ESTRATEGIAS DO'!F$5:H26,3,FALSE) -> Expandirse a regiones estratégicas con showrooms móviles y alianzas locales para captar demanda creciente.
D22: E7 | E22: =VLOOKUP(D22,'ESTRATEGIAS FA'!F11:H27,3,FALSE) -> Incentivar la compra mediante beneficios postventa (mantenimientos incluidos, garantías extendidas) para compensar la barrera del crédito. | F22: E7 | G22: =VLOOKUP(F12,'ESTRATEGIAS DO'!F$5:H27,3,FALSE) -> Invertir en soluciones de conectividad y servicios digitales asociados a vehículos conectados.
D23: E8 | E23: =VLOOKUP(D23,'ESTRATEGIAS FA'!F12:H28,3,FALSE) -> 0 | F23: E8 | G23: =VLOOKUP(F13,'ESTRATEGIAS DO'!F$5:H28,3,FALSE) -> Ingresar al mercado corporativo/estatal aprovechando que los altos requisitos excluyen a nuevos competidores.
D24: E9 | E24: =VLOOKUP(D24,'ESTRATEGIAS FA'!F13:H29,3,FALSE) -> 0 | F24: E9 | G24: =VLOOKUP(F14,'ESTRATEGIAS DO'!F$5:H29,3,FALSE) -> 0
D25: E10 | E25: =VLOOKUP(D25,'ESTRATEGIAS FA'!F14:H30,3,FALSE) -> 0 | F25: E10 | G25: =VLOOKUP(F15,'ESTRATEGIAS DO'!F$5:H30,3,FALSE) -> 0

Sheet ESTRATEGIAS FO
B1: CASO DE ESTUDIO: UNIVERSIDAD PERUANA UNIÓN Análisis del CAME
B2: FORTALEZAS - OPORTUNIDADES
B4: FORTALEZAS | D4: OPORTUNIDADES | F4: COD | G4: ESTRATEGIAS OFENSIVA
B5: F1 | C5: Experiencia consolidada en el rubro automotriz nacional. | D5: O1 | E5: Crecimiento de canales digitales y redes sociales para mejorar experiencia de compra | F5: E1 | G5: F4 + O1 | H5: Potenciar el CRM y la plataforma digital para captar clientes vía redes sociales y automatizar cotizaciones y seguimiento.
B6: F2 | C6: Alianzas estratégicas con marcas internacionales. | D6: O2 | E6: Normas de Indecopi (garantía, postventa) que aumentan confianza del cliente | F6: E2 | G6: F5 + O6 | H6: Lanzar una línea que tenga motos y autos compactos siendo respaldada por la fortaleza de marca para atraer al segmento joven.
B7: F3 | C7: Personal técnico certificado y capacitado | D7: O3 | E7: Creciente demanda del consumidor por conectividad vehicular y control de vehículo vía aplicaciones móviles | F7: E3 | G7: F2 + O5 | H7: Introducir modelos híbridos/eléctricos mediante acuerdos internacionales y financiamiento verde para liderar la electromovilidad.
B8: F4 | C8: Implementación de sistemas digitales de ventas y CRM. | D8: O4 | E8: Altas inversiones requeridas en infraestructura como barrera de entrada para nuevos competidores | F8: E4 | G8: F8 + O8 | H8: Garantizar disponibilidad inmediata de SUVs/camionetas mediante logística optimizada, superando tiempos de entrega de la competencia.
B9: F5 | C9: Buen posicionamiento de marca y reputación comercial. | D9: O5 | E9: Creación del Fondo de Promoción de Electromovilidad (FONCOER) y financiamiento verde | F9: E5 | G9: F6 + O2 | H9: Fortalecer y estandarizar la postventa para cumplir y superar Indecopi, elevando la confianza y fidelización del cliente.
B10: F6 | C10: Políticas de servicio postventa y atención al cliente. | D10: O6 | E10: Mayor interés del público joven en movilidad personal (motos, autos) | F10: E6 | G10: F10 + O7 | H10: Crear una linea que impulse vehículos híbridos/eléctricos, alineados a la preferencia ambiental de segmentos premium.
B11: F7 | C11: Capacidad de adaptación a regulaciones ambientales. | D11: O7 | E11: Mayor conciencia ambiental entre segmentos ABC que impulsa preferencia por vehículos híbridos y eléctricos | F11: E7 | G11: F3 + O3 | H11: Ofrecer servicios avanzados de conectividad (telemetría, apps, diagnósticos remotos) gracias al personal técnico especializado.
B12: F8 | C12: Eficiencia en los procesos logísticos de importación y distribución. | D12: O8 | E12: Mayor demanda por vehículos utilitarios (SUV y camionetas) por seguridad y versatilidad | F12: E8 | G12: F1 + O9 | H12: Formar la red “Incamotors Network” integrando concesionarios medianos mediante experiencia operativa y procesos consolidados.
B13: F9 | C13: Sistema contable y de control interno automatizado. | D13: O9 | E13: Tendencia de concentración y consolidación entre grupos concesionarios que facilita alianzas estratégicas | F13: E9 | G13: F12 + O10 | H13: Implementar IA para personalizar ofertas y mejorar la experiencia del cliente basándose en el historial de satisfacción.
B14: F10 | C14: Implementación de prácticas de sostenibilidad (reciclaje, emisiones). | D14: O10 | E14: Disponibilidad en mercado de herramientas de IA para el sector automotriz | F14: E10 | G14: F11 + O8 | H14: Impulsar un portafolio premium de SUVs dirigido a segmentos de mayor valor alineado a la tendencia utilitaria.
B15: F11 | C15: Posicionamiento en segmentos de gama media y alta. | D15: O11
B16: F12 | C16: Alta satisfacción del cliente según encuestas internas. | D16: O12

Sheet ESTRATEGIAS FA
B1: CASO DE ESTUDIO: UNIVERSIDAD PERUANA UNIÓN Análisis del CAME
B2: FORTALEZAS - AMENAZAS
B4: FORTALEZAS | D4: AMENAZAS | F4: COD | G4: ESTRATEGIAS DEFENSIVA
B5: F1 | C5: Experiencia consolidada en el rubro automotriz nacional. | D5: A1 | E5: Volatilidad del tipo de cambio que encarece la importación de vehículos | F5: E1 | G5: F8 + A1 | H5: Reforzar la consolidación de importaciones y la planificación de compras para reducir el impacto del tipo de cambio sobre el costo del vehículo.
B6: F2 | C6: Alianzas estratégicas con marcas internacionales. | D6: A2 | E6: Ingreso de fabricantes globales (Toyota, Honda, Nissan) que abren canales directos de distribución eliminando intermediarios | F6: E2 | G6: F2 + A2 | H6: Negociar acuerdos exclusivos y programas de fidelización con marcas aliadas para evitar ser desplazados por canales directos.
B7: F3 | C7: Personal técnico certificado y capacitado | D7: A3 | E7: Cambios frecuentes en legislación laboral y tributaria (AFP, EPS) que incrementan costos operacionales | F7: E3 | G7: F3 + A3 | H7: Optimizar productividad técnica mediante especialización y digitalización de procesos para compensar los mayores costos laborales.
B8: F4 | C8: Implementación de sistemas digitales de ventas y CRM. | D8: A4 | E8: Normativas del MTC que obligan incorporación de tecnologías de seguridad (ABS, airbag, control estabilidad) | F8: E4 | G8: F4 + A4 | H8: Integrar módulos digitales de seguimiento técnico para asegurar cumplimiento y actualización de tecnologías obligatorias.
B9: F5 | C9: Buen posicionamiento de marca y reputación comercial. | D9: A5 | E9: Tasas de interés (TEA) elevadas que limitan el acceso al crédito vehicular | F9: E5 | G9: F7 + A8 | H9: Fortalecer procesos de reducción de emisiones y trazabilidad ambiental para minimizar multas y adelantarse a regulaciones.
B10: F6 | C10: Políticas de servicio postventa y atención al cliente. | D10: A6 | E10: Competencia con marcas globales de alto prestigio y gran poder de negociación | F10: E6 | G10: F11 + A6 | H10: Diferenciar el portafolio con paquetes de valor, servicio boutique y garantías premium para competir frente a marcas de mayor prestigio.
B11: F7 | C11: Capacidad de adaptación a regulaciones ambientales. | D11: A7 | E11: Ausencia de infraestructura de carga pública para vehículos eléctricos en Perú | F11: E7 | G11: F6 + A5 | H11: Incentivar la compra mediante beneficios postventa (mantenimientos incluidos, garantías extendidas) para compensar la barrera del crédito.
B12: F8 | C12: Eficiencia en los procesos logísticos de importación y distribución. | D12: A8 | E12: Regulaciones ambientales más estrictas sobre emisiones vehiculares | F12: E8
B13: F9 | C13: Sistema contable y de control interno automatizado. | F13: E9
B14: F10 | C14: Implementación de prácticas de sostenibilidad (reciclaje, emisiones). | F14: E10
B15: F11 | C15: Posicionamiento en segmentos de gama media y alta. | F15: E11
B16: F12 | C16: Alta satisfacción del cliente según encuestas internas. | F16: E12

Sheet ESTRATEGIAS DO
B1: CASO DE ESTUDIO: UNIVERSIDAD PERUANA UNIÓN Análisis del CAME
B2: DEBILIDADES - OPORTUNIDADES
B4: DEBILIDADES | D4: OPORTUNIDADES | F4: COD | G4: ESTRATEGIAS ADAPTATIVAS
B5: F1 | C5: Alta dependencia de vehículos importados (vulnerable al tipo de cambio). | D5: A1 | E5: Crecimiento de canales digitales y redes sociales para mejorar experiencia de compra | F5: E1 | G5: D3 + O1 | H5: Digitalizar y automatizar procesos administrativos y comerciales integrando CRM, ventas online y atención digital.
B6: F2 | C6: Limitada oferta de vehículos eléctricos o híbridos. | D6: A2 | E6: Normas de Indecopi (garantía, postventa) que aumentan confianza del cliente | F6: E2 | G6: D11 + O10 | H6: Implementar IA para personalizar ofertas, recomendar modelos y automatizar propuestas comerciales.
B7: F3 | C7: Procesos administrativos poco automatizados. | D7: A3 | E7: Creciente demanda del consumidor por conectividad vehicular y control de vehículo vía aplicaciones móviles | F7: E3 | G7: D2 + O5 | H7: Expandir portafolio eco mediante alianzas estratégicas y uso del FONCOER para ingresar al mercado eléctrico.
B8: F4 | C8: Falta de diversificación en líneas de negocio. | D8: A4 | E8: Altas inversiones requeridas en infraestructura como barrera de entrada para nuevos competidores | F8: E4 | G8: D1 + O9 | H8: Integrarse a redes de concesionarios para compras conjuntas, economías de escala y reducción del riesgo cambiario.
B9: F5 | C9: Escasa presencia en regiones fuera de Lima. | D9: A5 | E9: Creación del Fondo de Promoción de Electromovilidad (FONCOER) y financiamiento verde | F9: E5 | G9: D8 + O6 | H9: Establecer convenios con financieras/fintech para ofrecer créditos accesibles a jóvenes (autos compactos, motos).
B10: F6 | C10: Dependencia de proveedores extranjeros. | D10: A6 | E10: Mayor interés del público joven en movilidad personal (motos, autos) | F10: E6 | G10: D5 + O8 | H10: Expandirse a regiones estratégicas con showrooms móviles y alianzas locales para captar demanda creciente.
B11: F7 | C11: Baja inversión en innovación tecnológica. | D11: A7 | E11: Mayor conciencia ambiental entre segmentos ABC que impulsa preferencia por vehículos híbridos y eléctricos | F11: E7 | G11: D7 + O3 | H11: Invertir en soluciones de conectividad y servicios digitales asociados a vehículos conectados.
B12: F8 | C12: Falta de alianzas financieras para crédito vehicular. | D12: A8 | E12: Mayor demanda por vehículos utilitarios (SUV y camionetas) por seguridad y versatilidad | F12: E8 | G12: D10 + O4 | H12: Ingresar al mercado corporativo/estatal aprovechando que los altos requisitos excluyen a nuevos competidores.
B13: F9 | C13: Ausencia de un sistema robusto de evaluación del desempeño. | D13: A9 | E13: Tendencia de concentración y consolidación entre grupos concesionarios que facilita alianzas estratégicas | F13: E9
B14: F10 | C14: Baja participación en licitaciones del sector público o corporativo. | D14: A10 | E14: Disponibilidad en mercado de herramientas de IA para el sector automotriz | F14: E10
B15: F11 | C15: Poca innovación en estrategias de ventas personalizadas | F15: E11
F16: E12
F17: E13

Sheet ESTRATEGIAS DA
B1: CASO DE ESTUDIO: UNIVERSIDAD PERUANA UNIÓN Análisis del CAME
B2: DEBILIDADES - AMENAZAS
B4: DEBILIDADES | D4: AMENAZAS | F4: COD | G4: ESTRATEGIAS DE SUPERVIVENCIA
B5: D1 | C5: Alta dependencia de vehículos importados (vulnerable al tipo de cambio). | D5: A1 | E5: Volatilidad del tipo de cambio que encarece la importación de vehículos | F5: E1 | G5: D1 + A1 | H5: Diversificar proveedores y asegurar compras programadas o contratos forward para reducir el impacto del tipo de cambio.
B6: D2 | C6: Limitada oferta de vehículos eléctricos o híbridos. | D6: A2 | E6: Ingreso de fabricantes globales (Toyota, Honda, Nissan) que abren canales directos de distribución eliminando intermediarios | F6: E2 | G6: D6 + A2 | H6: Negociar contratos de abastecimiento más estables y asegurar acuerdos mínimos para evitar ser desplazados por distribuidores directos.
B7: D3 | C7: Procesos administrativos poco automatizados. | D7: A3 | E7: Cambios frecuentes en legislación laboral y tributaria (AFP, EPS) que incrementan costos operacionales | F7: E3 | G7: D3 + A3 | H7: Implementar automatización básica (contable y RR.HH.) para evitar sanciones y sobrecostos por errores manuales.
B8: D4 | C8: Falta de diversificación en líneas de negocio. | D8: A4 | E8: Normativas del MTC que obligan incorporación de tecnologías de seguridad (ABS, airbag, control estabilidad) | F8: E4 | G8: D7 + A4 | H8: Asignar inversión mínima obligatoria para cumplir con tecnología reglamentaria (ABS, airbag), evitando multas y paralización de ventas.
B9: D5 | C9: Escasa presencia en regiones fuera de Lima. | D9: A5 | E9: Tasas de interés (TEA) elevadas que limitan el acceso al crédito vehicular | F9: E5 | G9: D8 + A5 | H9: Establecer convenios urgentes con financieras/fintech para evitar caída drástica en ventas por falta de acceso al crédito vehicular.
B10: D6 | C10: Dependencia de proveedores extranjeros. | D10: A6 | E10: Competencia con marcas globales de alto prestigio y gran poder de negociación | F10: E6 | G10: D2 + A7 | H10: Ajustar el portafolio eléctrico a modelos híbridos o mild-hybrid que no dependan de cargadores públicos para no perder competitividad.
B11: D7 | C11: Baja inversión en innovación tecnológica. | D11: A7 | E11: Ausencia de infraestructura de carga pública para vehículos eléctricos en Perú | F11: E7 | G11: D9 + A6 | H11: Implementar un sistema básico de evaluación de desempeño para alinear servicio, tiempos y calidad frente a competidores globales.
B12: D8 | C12: Falta de alianzas financieras para crédito vehicular. | D12: A8 | E12: Regulaciones ambientales más estrictas sobre emisiones vehiculares
B13: D9 | C13: Ausencia de un sistema robusto de evaluación del desempeño. | D13: A9
B14: D10 | C14: Baja participación en licitaciones del sector público o corporativo. | D14: A10
B15: D11 | C15: Poca innovación en estrategias de ventas personalizadas

Sheet FODA - CAME
D2: Fortaleza | E2: Debilidades
C3: FODA | D3: F1 Alta dependencia de vehículos importados (vulnerable al tipo de cambio). F2 Limitada oferta de vehículos eléctricos o híbridos. F3 Procesos administrativos poco automatizados. F4 Falta de diversificación en líneas de negocio. F5 Escasa presencia en regiones fuera de Lima. F6 Dependencia de proveedores extranjeros. F7 Baja inversión en innovación tecnológica. F8 Falta de alianzas financieras para crédito vehicular. F9 Ausencia de un sistema robusto de evaluación del desempeño. F10 Baja participación en licitaciones del sector público o corporativo. F11 Poca innovación en estrategias de ventas personalizadas | E3: D1 Alta dependencia de vehículos importados (vulnerable al tipo de cambio). D2 Limitada oferta de vehículos eléctricos o híbridos. D3 Procesos administrativos poco automatizados. D4 Falta de diversificación en líneas de negocio. D5 Escasa presencia en regiones fuera de Lima. D6 Dependencia de proveedores extranjeros. D7 Baja inversión en innovación tecnológica. D8 Falta de alianzas financieras para crédito vehicular. D9 Ausencia de un sistema robusto de evaluación del desempeño. D10 Baja participación en licitaciones del sector público o corporativo. D11 Poca innovación en estrategias de ventas personalizadas
C20: Oportunidades | D20: Estrategia Ofensiva | E20: Estrategia Adaptativa
C21: Teniendo en cuenta estas oportunidades O1 Crecimiento de canales digitales y redes sociales para mejorar experiencia de compra O2 Normas de Indecopi (garantía, postventa) que aumentan confianza del cliente O3 Creciente demanda del consumidor por conectividad vehicular y control de vehículo vía aplicaciones móviles O4 Altas inversiones requeridas en infraestructura como barrera de entrada para nuevos competidores O5 Creación del Fondo de Promoción de Electromovilidad (FONCOER) y financiamiento verde O6 Mayor interés del público joven en movilidad personal (motos, autos) O7 Mayor conciencia ambiental entre segmentos ABC que impulsa preferencia por vehículos híbridos y eléctricos O8 Mayor demanda por vehículos utilitarios (SUV y camionetas) por seguridad y versatilidad O9 Tendencia de concentración y consolidación entre grupos concesionarios que facilita alianzas estratégicas O10 Disponibilidad en mercado de herramientas de IA para el sector automotriz | D21: E1 Potenciar el CRM y la plataforma digital para captar clientes vía redes sociales y automatizar cotizaciones y seguimiento. E2 Lanzar una línea que tenga motos y autos compactos siendo respaldada por la fortaleza de marca para atraer al segmento joven. E3 Introducir modelos híbridos/eléctricos mediante acuerdos internacionales y financiamiento verde para liderar la electromovilidad. E4 Garantizar disponibilidad inmediata de SUVs/camionetas mediante logística optimizada, superando tiempos de entrega de la competencia. E5 Fortalecer y estandarizar la postventa para cumplir y superar Indecopi, elevando la confianza y fidelización del cliente. E6 Crear una linea que impulse vehículos híbridos/eléctricos, alineados a la preferencia ambiental de segmentos premium. E7 Ofrecer servicios avanzados de conectividad (telemetría, apps, diagnósticos remotos) gracias al personal técnico especializado. E8 Formar la red “Incamotors Network” integrando concesionarios medianos mediante experiencia operativa y procesos consolidados. E9 Implementar IA para personalizar ofertas y mejorar la experiencia del cliente basándose en el historial de satisfacción. E10 Impulsar un portafolio premium de SUVs dirigido a segmentos de mayor valor alineado a la tendencia utilitaria. | E21: E1 Digitalizar y automatizar procesos administrativos y comerciales integrando CRM, ventas online y atención digital. E2 Implementar IA para personalizar ofertas, recomendar modelos y automatizar propuestas comerciales. E3 Expandir portafolio eco mediante alianzas estratégicas y uso del FONCOER para ingresar al mercado eléctrico. E4 Integrarse a redes de concesionarios para compras conjuntas, economías de escala y reducción del riesgo cambiario. E5 Establecer convenios con financieras/fintech para ofrecer créditos accesibles a jóvenes (autos compactos, motos). E6 Expandirse a regiones estratégicas con showrooms móviles y alianzas locales para captar demanda creciente. E7 Invertir en soluciones de conectividad (apps, telemetría) y servicios digitales asociados a vehículos conectados. E8 Ingresar al mercado corporativo/estatal aprovechando que los altos requisitos excluyen a nuevos competidores.
C36: Amenazas | D36: Estrategia Defensiva | E36: Estrategia Supervivencia
C37: A1 Volatilidad del tipo de cambio que encarece la importación de vehículos A2 Ingreso de fabricantes globales (Toyota, Honda, Nissan) que abren canales directos de distribución eliminando intermediarios A3 Cambios frecuentes en legislación laboral y tributaria (AFP, EPS) que incrementan costos operacionales A4 Normativas del MTC que obligan incorporación de tecnologías de seguridad (ABS, airbag, control estabilidad) A5 Tasas de interés (TEA) elevadas que limitan el acceso al crédito vehicular A6 Competencia con marcas globales de alto prestigio y gran poder de negociación A7 Ausencia de infraestructura de carga pública para vehículos eléctricos en Perú A8 Regulaciones ambientales más estrictas sobre emisiones vehiculares | D37: E1 Reforzar la consolidación de importaciones y la planificación de compras para reducir el impacto del tipo de cambio sobre el costo del vehículo. E2 Negociar acuerdos exclusivos y programas de fidelización con marcas aliadas para evitar ser desplazados por canales directos. E3 Optimizar productividad técnica mediante especialización y digitalización de procesos para compensar los mayores costos laborales. E4 Integrar módulos digitales de seguimiento técnico para asegurar cumplimiento y actualización de tecnologías obligatorias. E5 Fortalecer procesos de reducción de emisiones y trazabilidad ambiental para minimizar multas y adelantarse a regulaciones. E6 Diferenciar el portafolio con paquetes de valor, servicio boutique y garantías premium para competir frente a marcas de mayor prestigio. E7 Incentivar la compra mediante beneficios postventa (mantenimientos incluidos, garantías extendidas) para compensar la barrera del crédito. | E37: E1 Diversificar proveedores y asegurar compras programadas o contratos forward para reducir el impacto del tipo de cambio. E2 Negociar contratos de abastecimiento más estables y asegurar acuerdos mínimos para evitar ser desplazados por distribuidores directos. E3 Implementar automatización básica (contable y RR.HH.) para evitar sanciones y sobrecostos por errores manuales. E4 Asignar inversión mínima obligatoria para cumplir con tecnología reglamentaria (ABS, airbag), evitando multas y paralización de ventas. E5 Establecer convenios urgentes con financieras/fintech para evitar caída drástica en ventas por falta de acceso al crédito vehicular. E6 Ajustar el portafolio eléctrico a modelos híbridos o mild-hybrid que no dependan de cargadores públicos para no perder competitividad. E7 Implementar un sistema básico de evaluación de desempeño para alinear servicio, tiempos y calidad frente a competidores globales.
